<replacements>
	<replacement>
		<from>Please insert startup disk</from>
		<to>GJ;FKEQCNF DCNFDMNT PFUHE</to>
	</replacement>
	<replacement>
		<from>
			Unable to find POOL.CFG
		</from>
		<to>YT ELF@NCZ YFQNB </to>
	</replacement>
	<replacement>
		<from>
			Overlay error, program abort!
		</from>
		<to>JIB&lt;RF JDTHKTZ GHJUHFVVF </to>
	</replacement>
	<replacement>
		<from>
			Phylactery
		</from>
		<to>ABKFRNTHBZ</to>
	</replacement>
	<replacement>
		<from>
			Token
		</from>
		<to>;TNJY</to>
	</replacement>
	<replacement>
		<from>
			Robe
		</from>
		<to>JLTZYBT</to>
	</replacement>
<!--	<replacement>
		<from>
			Cure Blindness
		</from>
		<to>CYZNBT CKTGJNS</to>
	</replacement>
	<replacement>
		<from>
			Cure Disease
		</from>
		<to>KTXTYBT &lt;JKTPYB</to>
	</replacement>
	<replacement>
		<from>
			Cure Light Wounds
		</from>
		<to>BCWTKTYBT K@URB[ HFY</to>
	</replacement>
	<replacement>
		<from>
			Cure Serious Wounds
		</from>
		<to>BCWTKTYBT UKE&lt;JRB[ HFY</to>
	</replacement>
	<replacement>
		<from>
			Cure Critical Wounds
		</from>
		<to>BPKTXTYBT RHBNBXTCRB[ HFY</to>
	</replacement>
	<replacement>
		<from>
			Neutralize Poison
		</from>
		<to>YTQNHFKBPFWBZ ZLF</to>
	</replacement>
	<replacement>
		<from>
			Raise Dead
		</from>
		<to>J;BDKTYBT</to>
	</replacement>
	<replacement>
		<from>
			Remove Curse
		</from>
		<to>CYZNBT GHJRKZNBZ</to>
	</replacement>
	<replacement>
		<from>
			Stone to Flesh
		</from>
		<to>RFVTYM D GKJNM</to>
	</replacement>-->
	<replacement>
		<from>
			Exit
		</from>
		<to>YFPFL</to>
	</replacement>
	<!--
	<replacement>
		<from>
			KOBOLD
		</from>
		<to>RJ&lt;JKML</to>
	</replacement>
	<replacement>
		<from>
			KOBOLD LEADER
		</from>
		<to>KBLTH RJ&lt;JKMLJD</to>
	</replacement>
	<replacement>
		<from>
			GOBLIN
		</from>
		<to>UJ&lt;KBY</to>
	</replacement>
	<replacement>
		<from>
			GOBLIN LEADER
		</from>
		<to>KBLTH UJ&lt;KBYJD</to>
	</replacement>
	<replacement>
		<from>
			ORC
		</from>
		<to>JHR</to>
	</replacement>
	<replacement>
		<from>
			ORC LEADER
		</from>
		<to>KBLTH JHRJD</to>
	</replacement>
	<replacement>
		<from>
			GOBLIN
		</from>
		<to>UJ&lt;KBY</to>
	</replacement>
	<replacement>
		<from>
			GOBLIN LEADER
		</from>
		<to>KBLTH UJ&lt;KBYJD</to>
	</replacement>
	<replacement>
		<from>
			HOBGOBLIN
		</from>
		<to>[J&lt;UJ&lt;KBY</to>
	</replacement>
	<replacement>
		<from>
			HOBGOBLIN CHIEF
		</from>
		<to>UKFDFHM [J&lt;UJ&lt;KBYJD</to>
	</replacement>
	<replacement>
		<from>
			GAGOOL
		</from>
		<to>UFUEKF</to>
	</replacement>
	<replacement>
		<from>
			MACE
		</from>
		<to>&lt;EKFDF</to>
	</replacement>
	<replacement>
		<from>
			OGRE
		</from>
		<to>JUH</to>
	</replacement>
	<replacement>
		<from>
			OGRE LEADER
		</from>
		<to>KBLTH JUHJD</to>
	</replacement>
	<replacement>
		<from>
			TROLL
		</from>
		<to>NHJKKM</to>
	</replacement>
	<replacement>
		<from>
			FIRE GIANT
		</from>
		<to>JUYTYYSQ DTKBRFY</to>
	</replacement>
	<replacement>
		<from>
			HILL GIANT
		</from>
		<to>[JKVJDJQ DTKBRFY</to>
	</replacement>-->
	<replacement>
		<from>
			Area Cast View Encamp Search Look
		</from>
		<to>RFHNF PFRK UTHJQ KFUTHM G</to>
	</replacement>
	<replacement>
		<from>
			Cast View Encamp Search Look
		</from>
		<to>PFRK UTHJQ KFUTHM GJBCR J</to>
	</replacement>
	<replacement>
		<from>
			Save View Magic Rest Alter Exit
		</from>
		<to>CJ[H UTHJQ VFUBZ JNLS[ YF</to>
	</replacement>
	<replacement>
		<from>
			Cast Memorize Scribe Display Rest Exit
		</from>
		<to>RJKLJD LJ&lt;FDBNM GTHTG PF</to>
	</replacement>
	<replacement>
		<from>
			Select Exit
		</from>
		<to>DS&lt;HFNM YFPFL</to>
	</replacement>
	<replacement>
		<from>
			Create New Character
		</from>
		<to>YJDSQ UTHJQ</to>
	</replacement>
	<replacement>
		<from>
			Drop Character
		</from>
		<to>ELFKBNM UTHJZ</to>
	</replacement>
	<replacement>
		<from>
			Modify Character
		</from>
		<to>VJLBABWBHJDFNM UTHJZ</to>
	</replacement>
	<replacement>
		<from>
			Train Character
		</from>
		<to>NHTYBHJDFNM UTHJZ</to>
	</replacement>
	<replacement>
		<from>
			View Character
		</from>
		<to>JCVJNHTNM UTHJZ</to>
	</replacement>
	<replacement>
		<from>
			Add Character to Party
		</from>
		<to>LJ&lt;FDBNM UTHJZ D JNHZL</to>
	</replacement>
	<replacement>
		<from>
			Remove Character from Party
		</from>
		<to>BPUYFNM UTHJZ BP JNHZLF</to>
	</replacement>
	<replacement>
		<from>
			Load Saved Game
		</from>
		<to>PFUHEPBNM BUHE</to>
	</replacement>
	<replacement>
		<from>
			Save Current Game
		</from>
		<to>CJ[HFYBNM BUHE</to>
	</replacement>
	<replacement>
		<from>
			BEGIN Adventuring
		</from>
		<to>GHBRK>XTYBT</to>
	</replacement>
	<replacement>
		<from>
			Exit to DOS
		</from>
		<to>DSQNB D LJC</to>
	</replacement>
	<replacement>
		<from>
			Parts color-1 color-2 Size Exit
		</from>
		<to>WDTN WDTN HJCN YFPFL</to>
	</replacement>
	<replacement>
		<from>
			Head Weapon Exit
		</from>
		<to>UJKJDF JHE;BT YFPFL</to>
	</replacement>
	<replacement>
		<from>
			$Weapon Body xxxx Shield Arm Leg Exit
		</from>
		<to>JHE;BT NTKJ  OBN HERF</to>
	</replacement>
	<replacement>
		<from>
			Keep Exit
		</from>
		<to>JCNFDBNM YFPFL</to>
	</replacement>
	<replacement>
		<from>
			Next Prev Keep Exit
		</from>
		<to>CKTL GHTL JCNFD YFPFL</to>
	</replacement>
	<replacement>
		<from>
			1st Level
		</from>
		<to>Q EHJDTYM</to>
	</replacement>
	<replacement>
		<from>
			2nd Level
		</from>
		<to>Q EHJDTYM</to>
	</replacement>
	<replacement>
		<from>
			3rd Level
		</from>
		<to>Q EHJDTYM</to>
	</replacement>
	<replacement>
		<from>
			4th Level
		</from>
		<to>Q EHJDTYM</to>
	</replacement>
	<replacement>
		<from>
			5th Level
		</from>
		<to>Q EHJDTYM</to>
	</replacement>
	<replacement>
		<from>
			6th Level
		</from>
		<to>Q EHJDTYM</to>
	</replacement>
	<replacement>
		<from>
			7th Level
		</from>
		<to>Q EHJDTYM</to>
	</replacement>
	<replacement>
		<from>
			8th Level
		</from>
		<to>Q EHJDTYM</to>
	</replacement>
	<replacement>
		<from>
			9th Level
		</from>
		<to>Q EHJDTYM</to>
	</replacement>
	<replacement>
		<from>
			Cleric
		</from>
		<to>;HTW</to>
	</replacement>
	<replacement>
		<from>
			Druid
		</from>
		<to>LHEBL</to>
	</replacement>
	<replacement>
		<from>
			Fighter
		</from>
		<to>&lt;JTW</to>
	</replacement>
	<replacement>
		<from>
			Paladin
		</from>
		<to>GFKFLBY</to>
	</replacement>
	<replacement>
		<from>
			Ranger
		</from>
		<to>CKTLJGSN</to>
	</replacement>
	<replacement>
		<from>
			Magic-User
		</from>
		<to>VFU</to>
	</replacement>
	<replacement>
		<from>
			Thief
		</from>
		<to>DJH</to>
	</replacement>
	<replacement>
		<from>
			Monk
		</from>
		<to>VJYF[</to>
	</replacement>
	<replacement>
		<from>
			Cleric/Fighter
		</from>
		<to>;HTW&lt;JTW</to>
	</replacement>
	<replacement>
		<from>
			Cleric/Fighter/Magic-User
		</from>
		<to>;HTW&lt;JTWVFU</to>
	</replacement>
	<replacement>
		<from>
			Cleric/Ranger
		</from>
		<to>;HTWCKTLJGSN</to>
	</replacement>
	<replacement>
		<from>
			Cleric/Magic-User
		</from>
		<to>;HTWVFU</to>
	</replacement>
	<replacement>
		<from>
			Cleric/Thief
		</from>
		<to>;HTWDJH</to>
	</replacement>
	<replacement>
		<from>
			Fighter/Magic-User
		</from>
		<to>&lt;JTWVFU</to>
	</replacement>
	<replacement>
		<from>
			Fighter/Thief
		</from>
		<to>&lt;JTWDJH</to>
	</replacement>
	<replacement>
		<from>
			Fighter/Magic-User/Thief
		</from>
		<to>&lt;JTWVFUDJH</to>
	</replacement>
	<replacement>
		<from>
			Magic-User/Thief
		</from>
		<to>VFUDJH</to>
	</replacement>
	<replacement>
		<from>
			Monster
		</from>
		<to>VJYCNH</to>
	</replacement>
	<replacement>
		<from>
			Dwarf
		</from>
		<to>LDJHA</to>
	</replacement>
	<replacement>
		<from>
			Elf
		</from>
		<to>'KMA</to>
	</replacement>
	<replacement>
		<from>
			Gnome
		</from>
		<to>UYJV</to>
	</replacement>
	<replacement>
		<from>
			Half-Elf
		</from>
		<to>GJKE'KMA</to>
	</replacement>
	<replacement>
		<from>
			Halfling
		</from>
		<to>GJKEHJCKBR</to>
	</replacement>
	<replacement>
		<from>
			Half-Orc
		</from>
		<to>GJKEJHR</to>
	</replacement>
	<replacement>
		<from>
			Human
		</from>
		<to>XTKJDTR</to>
	</replacement>
	<replacement>
		<from>
			Lawful Good
		</from>
		<to>PFRJYJGJCKEIYSQ LJ&lt;HSQ</to>
	</replacement>
	<replacement>
		<from>
			Lawful Neutral
		</from>
		<to>PFRJYJGJCKEIYSQ YTQNHFK</to>
	</replacement>
	<replacement>
		<from>
			Lawful Evil
		</from>
		<to>PFRJYJGJCKEIYSQ PKJQ</to>
	</replacement>
	<replacement>
		<from>
			Neutral Good
		</from>
		<to>LJ&lt;HSQ YTQNHFK</to>
	</replacement>
	<replacement>
		<from>
			True Neutral
		</from>
		<to>BCNBYYSQ YTQNHFK</to>
	</replacement>
	<replacement>
		<from>
			Neutral Evil
		</from>
		<to>PKJQ YTQNHFK</to>
	</replacement>
	<replacement>
		<from>
			Chaotic Good
		</from>
		<to>[FJNBXYJ LJ&lt;HSQ</to>
	</replacement>
	<replacement>
		<from>
			Chaotic Neutral
		</from>
		<to>[FJNBXYJ YTQNHFKMYSQ</to>
	</replacement>
	<replacement>
		<from>
			Chaotic Evil
		</from>
		<to>[FJNBXYJ PKJQ</to>
	</replacement>
	<replacement>
		<from>
			Male
		</from>
		<to>VE;XBYF</to>
	</replacement>
	<replacement>
		<from>
			Female
		</from>
		<to>;TYOBYF</to>
	</replacement><!--
	<replacement>
		<from>
			Copper
		</from>
		<to>VTLZRB</to>
	</replacement>
	<replacement>
		<from>
			Silver
		</from>
		<to>CTHT&lt;HJ</to>
	</replacement>
	<replacement>
		<from>
			Electrum
		</from>
		<to>'KTRNHEV</to>
	</replacement>
	<replacement>
		<from>
			Gold
		</from>
		<to>PJKJNJ</to>
	</replacement>
	<replacement>
		<from>
			Platinum
		</from>
		<to>GKFNBYF</to>
	</replacement>
	<replacement>
		<from>
			Gems
		</from>
		<to>CFVJWDTNS</to>
	</replacement>
	<replacement>
		<from>
			Jewelry
		</from>
		<to>LHFUJWTYYJCNB</to>
	</replacement>
	<replacement>
		<from>
			Okay
		</from>
		<to>KFLYJ</to>
	</replacement>
	<replacement>
		<from>
			Animated
		</from>
		<to>J;BDIBQ</to>
	</replacement>
	<replacement>
		<from>
			Running
		</from>
		<to>&lt;T;BN</to>
	</replacement>
	<replacement>
		<from>
			Unconscious
		</from>
		<to>&lt;TP CJPYFYBZ</to>
	</replacement>
	<replacement>
		<from>
			Dying
		</from>
		<to>EVBHFTN</to>
	</replacement>
	<replacement>
		<from>
			Dead
		</from>
		<to>V@HND</to>
	</replacement>
	<replacement>
		<from>
			Stoned
		</from>
		<to>JRFVTYTK</to>
	</replacement>
	<replacement>
		<from>
			Gone
		</from>
		<to>BCXTP</to>
	</replacement>
	<replacement>
		<from>
			Battle Axe
		</from>
		<to>&lt;JTDJQ NJGJH</to>
	</replacement>
	<replacement>
		<from>
			Hand Axe
		</from>
		<to>NJGJHBR</to>
	</replacement>
	<replacement>
		<from>
			Bardiche
		</from>
		<to>&lt;THLSI</to>
	</replacement>
	<replacement>
		<from>
			Bec De Corbin
		</from>
		<to>&lt;TR LT RJH&lt;BY</to>
	</replacement>
	<replacement>
		<from>
			Bill-Guisarme
		</from>
		<to>&lt;BKKMUBPFHVF</to>
	</replacement>
	<replacement>
		<from>
			Bo Stick
		</from>
		<to>GJCJ[ &lt;J</to>
	</replacement>
	<replacement>
		<from>
			Club
		</from>
		<to>LE&lt;BYF</to>
	</replacement>
	<replacement>
		<from>
			Dagger
		</from>
		<to>RBY;FK</to>
	</replacement>
	<replacement>
		<from>
			Dart
		</from>
		<to>LHJNBR</to>
	</replacement>
	<replacement>
		<from>
			Fauchard
		</from>
		<to>AJIFH</to>
	</replacement>
	<replacement>
		<from>
			Fauchard-Fork
		</from>
		<to>AFKMIFHLF</to>
	</replacement>
	<replacement>
		<from>
			Flail
		</from>
		<to>WTG</to>
	</replacement>
	<replacement>
		<from>
			Military Fork
		</from>
		<to>HJUFNBYF</to>
	</replacement>
	<replacement>
		<from>
			Glaive
		</from>
		<to>UKTAF</to>
	</replacement>
	<replacement>
		<from>
			Glaive-Guisarme
		</from>
		<to>UKTAFUBPFHVF</to>
	</replacement>
	<replacement>
		<from>
			Guisarme
		</from>
		<to>UBPFHVF</to>
	</replacement>
	<replacement>
		<from>
			Guisarme-Voulge
		</from>
		<to>UBPFHVFDEKM;</to>
	</replacement>
	<replacement>
		<from>
			Halberd
		</from>
		<to>FKT&lt;FHLF</to>
	</replacement>
	<replacement>
		<from>
			Lucern Hammer
		</from>
		<to>K>WTHYCRBQ VJKJN</to>
	</replacement>
	<replacement>
		<from>
			Hammer
		</from>
		<to>VJKJN</to>
	</replacement>
	<replacement>
		<from>
			Javelin
		</from>
		<to>K@URJT RJGM@</to>
	</replacement>
	<replacement>
		<from>
			Jo Stick
		</from>
		<to>GJCJ[ L;J</to>
	</replacement>
	<replacement>
		<from>
			Mace
		</from>
		<to>&lt;EKFDF</to>
	</replacement>
	<replacement>
		<from>
			Morning Star
		</from>
		<to>VJHUTYINTHY</to>
	</replacement>
	<replacement>
		<from>
			Partisan
		</from>
		<to>GHJNFPFY</to>
	</replacement>
	<replacement>
		<from>
			Military Pick
		</from>
		<to>RKTDTW</to>
	</replacement>
	<replacement>
		<from>
			Awl Pike
		</from>
		<to>FKMIGBC</to>
	</replacement>
	<replacement>
		<from>
			Scimitar
		</from>
		<to>ZNFUFY</to>
	</replacement>
	<replacement>
		<from>
			Spear
		</from>
		<to>RJGM@</to>
	</replacement>
	<replacement>
		<from>
			Spetum
		</from>
		<to>CGTNEV</to>
	</replacement>
	<replacement>
		<from>
			Quarter Staff
		</from>
		<to>GJCJ[</to>
	</replacement>
	<replacement>
		<from>
			Bastard Sword
		</from>
		<to>GJKENJHYSQ VTX</to>
	</replacement>
	<replacement>
		<from>
			Broad Sword
		</from>
		<to>IBHJRBQ VTX</to>
	</replacement>
	<replacement>
		<from>
			Long Sword
		</from>
		<to>LKBYYSQ VTX</to>
	</replacement>
	<replacement>
		<from>
			Short Sword
		</from>
		<to>RJHJNRBQ VTX</to>
	</replacement>
	<replacement>
		<from>
			Two-Handed Sword
		</from>
		<to>LDEHEXYSQ VTX</to>
	</replacement>
	<replacement>
		<from>
			Trident
		</from>
		<to>NHTPE&lt;TW</to>
	</replacement>
	<replacement>
		<from>
			Voulge
		</from>
		<to>DEKM;</to>
	</replacement>
	<replacement>
		<from>
			Composite Long Bow
		</from>
		<to>CJCNFDYJQ LKBYYSQ KER</to>
	</replacement>
	<replacement>
		<from>
			Composite Short Bow
		</from>
		<to>CJCNFDYJQ RJHJNRBQ KER</to>
	</replacement>
	<replacement>
		<from>
			Long Bow
		</from>
		<to>LKBYYSQ KER</to>
	</replacement>
	<replacement>
		<from>
			Short Bow
		</from>
		<to>RJHJNRBQ KER</to>
	</replacement>
	<replacement>
		<from>
			Heavy Crossbow
		</from>
		<to>NZ;@KSQ FH&lt;FKTN</to>
	</replacement>
	<replacement>
		<from>
			Light Crossbow
		</from>
		<to>K@URBQ FH&lt;FKTN</to>
	</replacement>
	<replacement>
		<from>
			Sling
		</from>
		<to>GHFOF</to>
	</replacement>
	<replacement>
		<from>
			Mail Armor
		</from>
		<to>LJCGT[&lt;HJYZ</to>
	</replacement>
	<replacement>
		<from>
			Leather
		</from>
		<to>RJ;FYSQ</to>
	</replacement>
	<replacement>
		<from>
			Padded
		</from>
		<to>CN@UFYSQ</to>
	</replacement>
	<replacement>
		<from>
			Studded
		</from>
		<to>RK@GFYSQ</to>
	</replacement>
	<replacement>
		<from>
			Ring
		</from>
		<to>RJKMXFNSQ</to>
	</replacement>
	<replacement>
		<from>
			Scale
		</from>
		<to>XTIEQXFNSQ</to>
	</replacement>
	<replacement>
		<from>
			Chain
		</from>
		<to>RJKMXE;YSQ</to>
	</replacement>
	<replacement>
		<from>
			Splint
		</from>
		<to>KFNYSQ</to>
	</replacement>
	<replacement>
		<from>
			Banded
		</from>
		<to>YF&lt;JHYSQ</to>
	</replacement>
	<replacement>
		<from>
			Plate
		</from>
		<to>GKFCNBYXFNFZ</to>
	</replacement>
	<replacement>
		<from>
			Shield
		</from>
		<to>OBN</to>
	</replacement>
	<replacement>
		<from>
			Arrow
		</from>
		<to>CNHTKF</to>
	</replacement>
	<replacement>
		<from>
			Potion
		</from>
		<to>PTKMT</to>
	</replacement>
	<replacement>
		<from>
			Scroll
		</from>
		<to>CDBNJR</to>
	</replacement>
	<replacement>
		<from>
			Ring
		</from>
		<to>RJKMWJ</to>
	</replacement>
	<replacement>
		<from>
			Talisman
		</from>
		<to>NFKBCVFY</to>
	</replacement>
	<replacement>
		<from>
			Gaseous Form
		</from>
		<to>UFPJJ&lt;HFPYFZ AJHVF</to>
	</replacement>
	<replacement>
		<from>
			Flying
		</from>
		<to>GJK@N</to>
	</replacement>
	<replacement>
		<from>
			Treasure Finding
		</from>
		<to>GJBCR CJRHJDBO</to>
	</replacement>
	<replacement>
		<from>
			Fear
		</from>
		<to>CNHF[</to>
	</replacement>
	<replacement>
		<from>
			Lightning Bolt
		</from>
		<to>VJKYBZ</to>
	</replacement>
	<replacement>
		<from>
			Fire Resistance
		</from>
		<to>CJGHJNBDKTYBT JUY></to>
	</replacement>
	<replacement>
		<from>
			Magic Missiles
		</from>
		<to>DJKIT&lt;YST CYFHZLS</to>
	</replacement>
	<replacement>
		<from>
			Clerical Scroll
		</from>
		<to>CDBNJR ;HTWF</to>
	</replacement>
	<replacement>
		<from>
			Magic User Scroll
		</from>
		<to>CDBNJR VFUF</to>
	</replacement>
	<replacement>
		<from>
			Protection Scroll
		</from>
		<to>CDBNJR PFOBNS</to>
	</replacement>
	<replacement>
		<from>
			Jewelry
		</from>
		<to>>DTKBHYST ERHFITYBZ</to>
	</replacement>
	<replacement>
		<from>
			Key
		</from>
		<to>RK>X</to>
	</replacement>
	<replacement>
		<from>
			AC 2
		</from>
		<to>R&lt; </to>
	</replacement>
	<replacement>
		<from>
			AC 6
		</from>
		<to>R&lt; </to>
	</replacement>
	<replacement>
		<from>
			AC 4
		</from>
		<to>R&lt; </to>
	</replacement>
	<replacement>
		<from>
			AC 3
		</from>
		<to>R&lt; </to>
	</replacement>
	<replacement>
		<from>
			Of Protection
		</from>
		<to>PFOBNS</to>
	</replacement>
	<replacement>
		<from>
			Paralyzation
		</from>
		<to>GFHFKBX</to>
	</replacement>
	<replacement>
		<from>
			Ogre Power
		</from>
		<to>VJOM JUHJD</to>
	</replacement>
	<replacement>
		<from>
			Invisibility
		</from>
		<to>YTDBLBVJCNM</to>
	</replacement>
	<replacement>
		<from>
			Missiles
		</from>
		<to>CYFHZLS</to>
	</replacement>
	<replacement>
		<from>
			Elvenkind
		</from>
		<to>'KMABQCRBQ</to>
	</replacement>
	<replacement>
		<from>
			Rotting
		</from>
		<to>UYBTYBT</to>
	</replacement>
	<replacement>
		<from>
			Covered
		</from>
		<to>GJRHSNSQ</to>
	</replacement>
	<replacement>
		<from>
			Efreeti
		</from>
		<to>'AHBN</to>
	</replacement>
	<replacement>
		<from>
			Bottle
		</from>
		<to>AKFRJY</to>
	</replacement>
	<replacement>
		<from>
			Missile Attractor
		</from>
		<to>FNNHFRNJH CYFHZLJD</to>
	</replacement>
	<replacement>
		<from>
			Of Maglubiyet
		</from>
		<to>GJHF;TYBZ</to>
	</replacement>
	<replacement>
		<from>
			Secr Door &amp; Trap Det
		</from>
		<to>CTRH LDTHM B JGHTL KJD</to>
	</replacement>
	<replacement>
		<from>
			Giant Strength
		</from>
		<to>CBKF UBUFYNF</to>
	</replacement>
	<replacement>
		<from>
			Flame Tongue
		</from>
		<to>ZPSR GKFVTYB</to>
	</replacement>
	<replacement>
		<from>
			Fireballs
		</from>
		<to>JUY IFHS</to>
	</replacement>
	<replacement>
		<from>
			Spiritual
		</from>
		<to>CDZOTYYSQ</to>
	</replacement>
	<replacement>
		<from>
			Boulder
		</from>
		<to>DFKEY</to>
	</replacement>
	<replacement>
		<from>
			Diamond
		</from>
		<to>FKVFP</to>
	</replacement>
	<replacement>
		<from>
			Emerald
		</from>
		<to>BPEVHEL</to>
	</replacement>
	<replacement>
		<from>
			Opal
		</from>
		<to>JGFK</to>
	</replacement>
	<replacement>
		<from>
			Saphire
		</from>
		<to>CFGABH</to>
	</replacement>
	<replacement>
		<from>
			Of Tyr
		</from>
		<to>NBHF</to>
	</replacement>
	<replacement>
		<from>
			Of Tempus
		</from>
		<to>NTVGECF</to>
	</replacement>
	<replacement>
		<from>
			Of Sune
		</from>
		<to>CEY'</to>
	</replacement>
	<replacement>
		<from>
			Wooden
		</from>
		<to>LTHTDZYYSQ</to>
	</replacement>
	<replacement>
		<from>
			#ERROR!
		</from>
		<to>#ERROR!</to>
	</replacement>
	<replacement>
		<from>
			Cursed
		</from>
		<to>GHJRKZNSQ</to>
	</replacement>
	<replacement>
		<from>
			N
		</from>
		<to>C</to>
	</replacement>
	<replacement>
		<from>
			NE
		</from>
		<to>CD</to>
	</replacement>
	<replacement>
		<from>
			E
		</from>
		<to>D</to>
	</replacement>
	<replacement>
		<from>
			SE
		</from>
		<to>>D</to>
	</replacement>
	<replacement>
		<from>
			S
		</from>
		<to>></to>
	</replacement>
	<replacement>
		<from>
			SW
		</from>
		<to>>P</to>
	</replacement>
	<replacement>
		<from>
			W
		</from>
		<to>P</to>
	</replacement>
	<replacement>
		<from>
			NW
		</from>
		<to>CP</to>
	</replacement>
	<replacement>
		<from>
			Insert disk 1 in drive
		</from>
		<to>DCNFDMNT LBCRTNE  D GHBDJ</to>
	</replacement>
	<replacement>
		<from>
			Insert disk 2 in drive
		</from>
		<to>DCNFDMNT LBCRTNE  D GHBDJ</to>
	</replacement>
	<replacement>
		<from>
			Insert disk 3 in drive
		</from>
		<to>DCNFDMNT LBCRTNE  D GHBDJ</to>
	</replacement>
	<replacement>
		<from>
			Insert disk 4 in drive
		</from>
		<to>DCNFDMNT LBCRTNE  D GHBDJ</to>
	</replacement>
	<replacement>
		<from>
			Insert disk 5 in drive
		</from>
		<to>DCNFDMNT LBCRTNE  D GHBDJ</to>
	</replacement>
	<replacement>
		<from>
			Insert disk 6 in drive
		</from>
		<to>DCNFDMNT LBCRTNE  D GHBDJ</to>
	</replacement>
	<replacement>
		<from>
			Insert disk 7 in drive
		</from>
		<to>DCNFDMNT LBCRTNE  D GHBDJ</to>
	</replacement>
	<replacement>
		<from>
			Insert disk 8 in drive
		</from>
		<to>DCNFDMNT LBCRTNE  D GHBDJ</to>
	</replacement>
	<replacement>
		<from>
			Bless
		</from>
		<to>&lt;KFUJCKJDTYBT</to>
	</replacement>
	<replacement>
		<from>
			Curse
		</from>
		<to>GHJRKZNBT</to>
	</replacement>
	<replacement>
		<from>
			Cure Light Wounds
		</from>
		<to>BCWTKTYBT K@URB[ HFY</to>
	</replacement>
	<replacement>
		<from>
			Cause Light Wounds
		</from>
		<to>YFYTCTYBT K@URB[ HFY</to>
	</replacement>
	<replacement>
		<from>
			Detect Magic
		</from>
		<to>J&lt;YFHE;TYBT VFUBB</to>
	</replacement>
	<replacement>
		<from>
			Protection From Evil
		</from>
		<to>PFOBNF JN PKF</to>
	</replacement>
	<replacement>
		<from>
			Protection from Good
		</from>
		<to>PFOBNF JN LJ&lt;HF</to>
	</replacement>
	<replacement>
		<from>
			Resist Cold
		</from>
		<to>CJGHJNBDKTYBT [JKJLE</to>
	</replacement>
	<replacement>
		<from>
			Burning Hands
		</from>
		<to>GSKF>OBT HERB</to>
	</replacement>
	<replacement>
		<from>
			Charm Person
		</from>
		<to>JXFHJDFYBT KBXYJCNB</to>
	</replacement>
	<replacement>
		<from>
			Detect Magic
		</from>
		<to>J&lt;YFHE;TYBT VFUBB</to>
	</replacement>
	<replacement>
		<from>
			Enlarge
		</from>
		<to>EDTKBXTYBT</to>
	</replacement>
	<replacement>
		<from>
			Reduce
		</from>
		<to>EVTYMITYBT</to>
	</replacement>
	<replacement>
		<from>
			Friends
		</from>
		<to>LHE;&lt;F</to>
	</replacement>
	<replacement>
		<from>
			Magic Missile
		</from>
		<to>DJKIT&lt;YFZ CNHTKF</to>
	</replacement>
	<replacement>
		<from>
			Protection From Evil
		</from>
		<to>PFOBNF JN PKF</to>
	</replacement>
	<replacement>
		<from>
			Protection From Good
		</from>
		<to>PFOBNF JN LJ&lt;HF</to>
	</replacement>
	<replacement>
		<from>
			Read Magic
		</from>
		<to>XNTYBT VFUBB</to>
	</replacement>
	<replacement>
		<from>
			Shield
		</from>
		<to>OBN</to>
	</replacement>
	<replacement>
		<from>
			Shocking Grasp
		</from>
		<to>'KTRNHJIJR</to>
	</replacement>
	<replacement>
		<from>
			Sleep
		</from>
		<to>CJY</to>
	</replacement>
	<replacement>
		<from>
			Find Traps
		</from>
		<to>YFQNB KJDEIRB</to>
	</replacement>
	<replacement>
		<from>
			Hold Person
		</from>
		<to>ELTH;FYBT KBXYJCNB</to>
	</replacement>
	<replacement>
		<from>
			Resist Fire
		</from>
		<to>CJGHJNBDKTYBT JUY></to>
	</replacement>
	<replacement>
		<from>
			Silence, 15' Radius
		</from>
		<to>YTVJNF HFLBEC V</to>
	</replacement>
	<replacement>
		<from>
			Slow Poison
		</from>
		<to>PFVTLKBNM ZL</to>
	</replacement>
	<replacement>
		<from>
			Snake Charm
		</from>
		<to>PVTBYSQ J&lt;THTU</to>
	</replacement>
	<replacement>
		<from>
			Spiritual Hammer
		</from>
		<to>CDZOTYYSQ VJKJN</to>
	</replacement>
	<replacement>
		<from>
			Detect Invisibility
		</from>
		<to>J&lt;YFHE;TYBT YTDBLBVJCNB</to>
	</replacement>
	<replacement>
		<from>
			Invisibility
		</from>
		<to>YTDBLBVJCNM</to>
	</replacement>
	<replacement>
		<from>
			Knock
		</from>
		<to>CNER</to>
	</replacement>
	<replacement>
		<from>
			Mirror Image
		</from>
		<to>JNHF;TYBT</to>
	</replacement>
	<replacement>
		<from>
			Ray of Enfeeblement
		</from>
		<to>KEX CKF&lt;JCNB</to>
	</replacement>
	<replacement>
		<from>
			Stinking Cloud
		</from>
		<to>PKJDJYYJT J&lt;KFRJ</to>
	</replacement>
	<replacement>
		<from>
			Strength
		</from>
		<to>CBKF</to>
	</replacement>
	<replacement>
		<from>
			Animate Dead
		</from>
		<to>J;BDKTYBT V@HNDJUJ</to>
	</replacement>
	<replacement>
		<from>
			Cure Blindness
		</from>
		<to>CYZNBT CKTGJNS</to>
	</replacement>
	<replacement>
		<from>
			Cause Blindness
		</from>
		<to>JCKTGKTYBT</to>
	</replacement>
	<replacement>
		<from>
			Cure Disease
		</from>
		<to>CYZNBT &lt;JKTPYB</to>
	</replacement>
	<replacement>
		<from>
			Cause Disease
		</from>
		<to>&lt;JKTPYM</to>
	</replacement>
	<replacement>
		<from>
			Dispel Magic
		</from>
		<to>HFCCTBDFYBT VFUBB</to>
	</replacement>
	<replacement>
		<from>
			Prayer
		</from>
		<to>VJKBNDF</to>
	</replacement>
	<replacement>
		<from>
			Remove Curse
		</from>
		<to>CYZNBT GHJRKZNBZ</to>
	</replacement>
	<replacement>
		<from>
			Bestow Curse
		</from>
		<to>GHJRKZNBT</to>
	</replacement>
	<replacement>
		<from>
			Blink
		</from>
		<to>VTHWFYBT</to>
	</replacement>
	<replacement>
		<from>
			Dispel Magic
		</from>
		<to>HFCCTBDFYBT VFUBB</to>
	</replacement>
	<replacement>
		<from>
			Fireball
		</from>
		<to>JUYTYYSQ IFH</to>
	</replacement>
	<replacement>
		<from>
			Haste
		</from>
		<to>ECRJHTYBT</to>
	</replacement>
	<replacement>
		<from>
			Hold Person
		</from>
		<to>ELTH;FYBT KBXYJCNB</to>
	</replacement>
	<replacement>
		<from>
			Invisibility, 10' Radius
		</from>
		<to>YTDBLBVJCNM HFLBEC V</to>
	</replacement>
	<replacement>
		<from>
			Lightning Bolt Protection From Evil, 10' Radius Protection From Good, 10' Radius
		</from>
		<to>VJKYBZ PFOBNF JN PKF HFLB</to>
	</replacement>
	<replacement>
		<from>
			Protection From Normal Missiles
		</from>
		<to>PFOBNF JN J&lt;SXYS[ VTNFNTKM</to>
	</replacement>
	<replacement>
		<from>
			Slow
		</from>
		<to>PFVTLKTYBT</to>
	</replacement>
	<replacement>
		<from>
			Restoration
		</from>
		<to>DJCCNFYJDKTYBT</to>
	</replacement>-->
</replacements>